setup.py
distributions_sw/Binomialdistribution.py
distributions_sw/Gaussiandistribution.py
distributions_sw/Generaldistribution.py
distributions_sw/__init__.py
distributions_sw.egg-info/PKG-INFO
distributions_sw.egg-info/SOURCES.txt
distributions_sw.egg-info/dependency_links.txt
distributions_sw.egg-info/not-zip-safe
distributions_sw.egg-info/top_level.txt